pykeydelivery/__init__.py
pykeydelivery/classes/__init__.py
pykeydelivery/classes/http.py
pykeydelivery/classes/keydelivery.py
pykeydelivery-0.9.1.dist-info/METADATA
pykeydelivery-0.9.1.dist-info/WHEEL
pykeydelivery-0.9.1.dist-info/licenses/LICENSE
pykeydelivery-0.9.1.dist-info/RECORD
