Metadata-Version: 2.1
Name: pykeydelivery
Version: 0.9.1
Summary: Simple Python wrapper to fetch data from KeyDelivery (kd100.com)
Project-URL: Homepage, https://kumig.it/kumitterer/pykeydelivery
Project-URL: Bug Tracker, https://kumig.it/kumitterer/pykeydelivery/issues
Author-email: Kumi Mitterer <pykeydelivery@kumi.email>
License: Copyright (c) 2023 Kumi Mitterer <pykeydelivery@kumi.email>
License-File: LICENSE
Classifier: License :: OSI Approved :: MIT License
Classifier: Operating System :: OS Independent
Classifier: Programming Language :: Python :: 3
Requires-Python: >=3.10
